[{"__type__":"cc.SpriteFrame","content":{"name":"haitac_mng_btn_item_1","texture":"8bm0rth5tNdaExwAPWtlvy","rect":[1073,1631,180,162],"offset":[0,0],"originalSize":[180,162],"rotated":1,"capInsets":[0,0,0,0]}},{"__type__":"cc.SpriteFrame","content":{"name":"haitac_top_bg_minigame","texture":"8bm0rth5tNdaExwAPWtlvy","rect":[1,723,1280,85],"offset":[0,0],"originalSize":[1280,85],"rotated":1,"capInsets":[0,0,0,0]}},{"__type__":"cc.SpriteFrame","content":{"name":"haitac_mng_btn_item_11","texture":"8bm0rth5tNdaExwAPWtlvy","rect":[1517,1600,128,128],"offset":[0,0],"originalSize":[128,128],"capInsets":[0,0,0,0]}},{"__type__":"cc.SpriteFrame","content":{"name":"haitac_mng_rw_1","texture":"8bm0rth5tNdaExwAPWtlvy","rect":[1563,220,57,55],"offset":[0,0],"originalSize":[57,55],"capInsets":[0,0,0,0]}},{"__type__":"cc.SpriteFrame","content":{"name":"haitac_mng_btn_item_7","texture":"8bm0rth5tNdaExwAPWtlvy","rect":[1104,1813,153,167],"offset":[0,0],"originalSize":[153,167],"capInsets":[0,0,0,0]}},{"__type__":"cc.SpriteFrame","content":{"name":"haitac_mng_btn_close","texture":"8bm0rth5tNdaExwAPWtlvy","rect":[1563,1,217,68],"offset":[0,0],"originalSize":[217,68],"rotated":1,"capInsets":[0,0,0,0]}},{"__type__":"cc.SpriteFrame","content":{"name":"haitac_mng_rw_3","texture":"8bm0rth5tNdaExwAPWtlvy","rect":[1563,220,57,55],"offset":[0,0],"originalSize":[57,55],"capInsets":[0,0,0,0]}},{"__type__":"cc.SpriteFrame","content":{"name":"haitac_mng_btn_item_8","texture":"8bm0rth5tNdaExwAPWtlvy","rect":[1390,1600,147,125],"offset":[0,0],"originalSize":[147,125],"rotated":1,"capInsets":[0,0,0,0]}},{"__type__":"cc.SpriteFrame","content":{"name":"haitac_mng_btn_item_4","texture":"8bm0rth5tNdaExwAPWtlvy","rect":[931,1631,183,140],"offset":[0,0],"originalSize":[183,140],"rotated":1,"capInsets":[0,0,0,0]}},{"__type__":"cc.SpriteFrame","content":{"name":"haitac_mng_btn_item_0","texture":"8bm0rth5tNdaExwAPWtlvy","rect":[1231,1445,152,171],"offset":[0,0],"originalSize":[152,171],"capInsets":[0,0,0,0]}},{"__type__":"cc.SpriteFrame","content":{"name":"haitac_mng_btn_item_10","texture":"8bm0rth5tNdaExwAPWtlvy","rect":[1385,1445,153,137],"offset":[0,0],"originalSize":[153,137],"rotated":1,"capInsets":[0,0,0,0]}},{"__type__":"cc.SpriteFrame","content":{"name":"haitac_mng_btn_item_5","texture":"8bm0rth5tNdaExwAPWtlvy","rect":[1259,1777,146,148],"offset":[0,0],"originalSize":[146,148],"capInsets":[0,0,0,0]}},{"__type__":"cc.SpriteFrame","content":{"name":"haitac_mng_btn_item_6","texture":"8bm0rth5tNdaExwAPWtlvy","rect":[931,1445,184,144],"offset":[0,0],"originalSize":[184,144],"rotated":1,"capInsets":[0,0,0,0]}},{"__type__":"cc.SpriteFrame","content":{"name":"haitac_mng_btn_item_3","texture":"8bm0rth5tNdaExwAPWtlvy","rect":[1077,1445,176,152],"offset":[0,0],"originalSize":[176,152],"rotated":1,"capInsets":[0,0,0,0]}},{"__type__":"cc.SpriteAtlas","_name":"slots_haitac_minigame.plist","_spriteFrames":{"haitac_bg_free":{"__uuid__":"eazjcPakNPmrahTWtQmMQF"},"haitac_bg_mng_text_1":{"__uuid__":"b16PUzO/BNjY2q9SlIexHg"},"haitac_bg_mng_text_2":{"__uuid__":"d5kH7S3mtBm6MAjOGdZL/8"},"haitac_mng_bg_1":{"__uuid__":"7f1EsJyT5GDZzgbpCdk06D"},"haitac_mng_bg_thongbao":{"__uuid__":"87U3xpAd1LV5AyUJ+3J4vf"},"haitac_mng_btn_close":{"__uuid__":"32luFJazFNs6WCQAYzvmgw"},"haitac_mng_btn_item_0":{"__uuid__":"57oRRncWpP0a21TbGvMwqX"},"haitac_mng_btn_item_1":{"__uuid__":"084SKoLXJBKr1Ng511Xn/4"},"haitac_mng_btn_item_10":{"__uuid__":"5erssihpFMFbGUCJMTUxRc"},"haitac_mng_btn_item_11":{"__uuid__":"24MXC8oqFH/qiCk7hjh859"},"haitac_mng_btn_item_2":{"__uuid__":"e9eC/UF6ZI7qbqftL2NtUd"},"haitac_mng_btn_item_3":{"__uuid__":"71glrKKv5FOL1BPgNkFcYv"},"haitac_mng_btn_item_4":{"__uuid__":"57UVdFf8xAvpdgvkQ7WUxP"},"haitac_mng_btn_item_5":{"__uuid__":"6bvTVNtTJAC5bCrom8Ca/C"},"haitac_mng_btn_item_6":{"__uuid__":"6eY3aRA6FMdoXUxCA7Ww1L"},"haitac_mng_btn_item_7":{"__uuid__":"2fiC9t5JdESI2PKFmWv+QD"},"haitac_mng_btn_item_8":{"__uuid__":"4edCSzxtNDpZOidkyu3NCK"},"haitac_mng_btn_item_9":{"__uuid__":"a0Bc0fNtBOSZg52CsJuyaS"},"haitac_mng_rw_0":{"__uuid__":"fcMlW4h2FDDYqQvlQ+ozkT"},"haitac_mng_rw_1":{"__uuid__":"29CwYqlARFjYEUBQgU6mbw"},"haitac_mng_rw_2":{"__uuid__":"db6KLDen1Hhrbb20Qb4KsT"},"haitac_mng_rw_3":{"__uuid__":"35A43pq7dDELX9nWWEuQD2"},"haitac_mng_rw_4":{"__uuid__":"b91CAJTmpAwLsXYH3wLiJf"},"haitac_outdoor_bg1":{"__uuid__":"7aYSuAMYhBfYHG2wWQcVRE"},"haitac_outdoor_bg2":{"__uuid__":"ffKVtoa+9NZLzXn4qdd5l2"},"haitac_top_bg_minigame":{"__uuid__":"0esY9zUrJHX6ecfRD1bINt"}}},{"__type__":"cc.SpriteFrame","content":{"name":"haitac_outdoor_bg1","texture":"8bm0rth5tNdaExwAPWtlvy","rect":[1,1,1560,720],"offset":[0,0],"originalSize":[1560,720],"capInsets":[0,0,0,0]}},{"__type__":"cc.SpriteFrame","content":{"name":"haitac_mng_bg_1","texture":"8bm0rth5tNdaExwAPWtlvy","rect":[1563,220,57,55],"offset":[0,0],"originalSize":[57,55],"capInsets":[0,0,0,0]}},{"__type__":"cc.SpriteFrame","content":{"name":"haitac_mng_bg_thongbao","texture":"8bm0rth5tNdaExwAPWtlvy","rect":[88,1445,841,508],"offset":[0,0],"originalSize":[841,508],"capInsets":[0,0,0,0]}},{"__type__":"cc.SpriteFrame","content":{"name":"haitac_mng_btn_item_9","texture":"8bm0rth5tNdaExwAPWtlvy","rect":[931,1816,171,181],"offset":[0,0],"originalSize":[171,181],"capInsets":[0,0,0,0]}},{"__type__":"cc.SpriteFrame","content":{"name":"haitac_bg_mng_text_1","texture":"8bm0rth5tNdaExwAPWtlvy","rect":[1563,220,57,55],"offset":[0,0],"originalSize":[57,55],"capInsets":[0,0,0,0]}},{"__type__":"cc.SpriteFrame","content":{"name":"haitac_mng_rw_4","texture":"8bm0rth5tNdaExwAPWtlvy","rect":[1563,220,57,55],"offset":[0,0],"originalSize":[57,55],"capInsets":[0,0,0,0]}},{"__type__":"cc.SpriteFrame","content":{"name":"haitac_bg_mng_text_2","texture":"8bm0rth5tNdaExwAPWtlvy","rect":[1563,220,57,55],"offset":[0,0],"originalSize":[57,55],"capInsets":[0,0,0,0]}},{"__type__":"cc.SpriteFrame","content":{"name":"haitac_mng_rw_2","texture":"8bm0rth5tNdaExwAPWtlvy","rect":[1563,220,57,55],"offset":[0,0],"originalSize":[57,55],"capInsets":[0,0,0,0]}},{"__type__":"cc.SpriteFrame","content":{"name":"haitac_mng_btn_item_2","texture":"8bm0rth5tNdaExwAPWtlvy","rect":[1237,1618,157,151],"offset":[0,0],"originalSize":[157,151],"rotated":1,"capInsets":[0,0,0,0]}},{"__type__":"cc.SpriteFrame","content":{"name":"haitac_bg_free","texture":"8bm0rth5tNdaExwAPWtlvy","rect":[88,723,1559,720],"offset":[0,0],"originalSize":[1559,720],"capInsets":[0,0,0,0]}},{"__type__":"cc.SpriteFrame","content":{"name":"haitac_mng_rw_0","texture":"8bm0rth5tNdaExwAPWtlvy","rect":[1524,1445,92,132],"offset":[0,0],"originalSize":[92,132],"capInsets":[0,0,0,0]}},{"__type__":"cc.SpriteFrame","content":{"name":"haitac_outdoor_bg2","texture":"8bm0rth5tNdaExwAPWtlvy","rect":[1,1,1560,720],"offset":[0,0],"originalSize":[1560,720],"capInsets":[0,0,0,0]}}]